mlhelper/__init__.py
mlhelper/lab1.py
mlhelper/lab10.py
mlhelper/lab2.py
mlhelper/lab3.py
mlhelper/lab4.py
mlhelper/lab5.py
mlhelper/lab6.py
mlhelper/lab7.py
mlhelper/lab8.py
mlhelper/lab9.py
mlhelper/utils.py
mlhelper2025-0.1.0.dist-info/METADATA
mlhelper2025-0.1.0.dist-info/WHEEL
mlhelper2025-0.1.0.dist-info/top_level.txt
mlhelper2025-0.1.0.dist-info/RECORD
