Metadata-Version: 2.4
Name: mlhelper2025
Version: 0.1.0
Summary: Lab experiment scripts with a print feature
Author: anon_e_mous
Requires-Python: >=3.6
Dynamic: author
Dynamic: requires-python
Dynamic: summary
